tensorflow-stubs/METADATA.toml
tensorflow-stubs/__init__.pyi
tensorflow-stubs/_aliases.pyi
tensorflow-stubs/audio.pyi
tensorflow-stubs/autodiff.pyi
tensorflow-stubs/bitwise.pyi
tensorflow-stubs/dtypes.pyi
tensorflow-stubs/initializers.pyi
tensorflow-stubs/linalg.pyi
tensorflow-stubs/math.pyi
tensorflow-stubs/nn.pyi
tensorflow-stubs/py.typed
tensorflow-stubs/random.pyi
tensorflow-stubs/raw_ops.pyi
tensorflow-stubs/signal.pyi
tensorflow-stubs/sparse.pyi
tensorflow-stubs/strings.pyi
tensorflow-stubs/summary.pyi
tensorflow-stubs/autograph/__init__.pyi
tensorflow-stubs/autograph/experimental.pyi
tensorflow-stubs/compiler/xla/xla_data_pb2.pyi
tensorflow-stubs/compiler/xla/xla_pb2.pyi
tensorflow-stubs/compiler/xla/service/hlo_pb2.pyi
tensorflow-stubs/compiler/xla/service/hlo_profile_printer_data_pb2.pyi
tensorflow-stubs/compiler/xla/service/metrics_pb2.pyi
tensorflow-stubs/compiler/xla/service/test_compilation_environment_pb2.pyi
tensorflow-stubs/compiler/xla/service/xla_compile_result_pb2.pyi
tensorflow-stubs/compiler/xla/tsl/protobuf/bfc_memory_map_pb2.pyi
tensorflow-stubs/compiler/xla/tsl/protobuf/test_log_pb2.pyi
tensorflow-stubs/config/__init__.pyi
tensorflow-stubs/config/experimental.pyi
tensorflow-stubs/core/example/example_parser_configuration_pb2.pyi
tensorflow-stubs/core/example/example_pb2.pyi
tensorflow-stubs/core/example/feature_pb2.pyi
tensorflow-stubs/core/framework/allocation_description_pb2.pyi
tensorflow-stubs/core/framework/api_def_pb2.pyi
tensorflow-stubs/core/framework/attr_value_pb2.pyi
tensorflow-stubs/core/framework/cost_graph_pb2.pyi
tensorflow-stubs/core/framework/cpp_shape_inference_pb2.pyi
tensorflow-stubs/core/framework/dataset_metadata_pb2.pyi
tensorflow-stubs/core/framework/dataset_options_pb2.pyi
tensorflow-stubs/core/framework/dataset_pb2.pyi
tensorflow-stubs/core/framework/device_attributes_pb2.pyi
tensorflow-stubs/core/framework/full_type_pb2.pyi
tensorflow-stubs/core/framework/function_pb2.pyi
types_tensorflow-2.18.0.20260121.dist-info/licenses/LICENSE
types_tensorflow-2.18.0.20260121.dist-info/METADATA
types_tensorflow-2.18.0.20260121.dist-info/WHEEL
types_tensorflow-2.18.0.20260121.dist-info/top_level.txt
types_tensorflow-2.18.0.20260121.dist-info/RECORD
