Metadata-Version: 2.4
Name: types-tensorflow
Version: 2.18.0.20260121
Summary: Typing stubs for tensorflow
License-Expression: Apache-2.0
Project-URL: Homepage, https://github.com/python/typeshed
Project-URL: GitHub, https://github.com/python/typeshed
Project-URL: Changes, https://github.com/typeshed-internal/stub_uploader/blob/main/data/changelogs/tensorflow.md
Project-URL: Issue tracker, https://github.com/python/typeshed/issues
Project-URL: Chat, https://gitter.im/python/typing
Classifier: Programming Language :: Python :: 3
Classifier: Typing :: Stubs Only
Requires-Python: >=3.9
License-File: LICENSE
Requires-Dist: types-protobuf
Requires-Dist: types-requests
Requires-Dist: numpy>=1.20
Dynamic: license-file
